AUTHORS
ChangeLog
MANIFEST.in
README.rst
requirements.txt
setup.cfg
setup.py
leonardo_translations/__init__.py
leonardo_translations/settings.py
leonardo_translations/urls.py
leonardo_translations.egg-info/PKG-INFO
leonardo_translations.egg-info/SOURCES.txt
leonardo_translations.egg-info/dependency_links.txt
leonardo_translations.egg-info/not-zip-safe
leonardo_translations.egg-info/pbr.json
leonardo_translations.egg-info/requires.txt
leonardo_translations.egg-info/top_level.txt