Metadata-Version: 1.1
Name: leonardo-translations
Version: 1.0.1
Summary: Rosetta ingation to leonardo-cms -> makes managing translations easy
Home-page: https://github.com/leonardo-modules/leonardo-translations.git
Author: Michael Kuty
Author-email: kutymichael@gmail.com
License: UNKNOWN
Platform: UNKNOWN
Classifier: Development Status :: 5 - Production/Stable
Classifier: Framework :: Django
Classifier: Intended Audience :: Developers
Classifier: License :: OSI Approved :: BSD License
Classifier: Operating System :: OS Independent
Classifier: Programming Language :: Python
Classifier: Programming Language :: Python :: 2.6
Classifier: Programming Language :: Python :: 2.7
Classifier: Programming Language :: Python :: 3
Classifier: Programming Language :: Python :: 3.3
Classifier: Programming Language :: Python :: 3.4
Classifier: Topic :: Software Development
Classifier: Topic :: Software Development :: Libraries :: Application Frameworks
